LICENSE
MANIFEST.in
README.md
setup.py
gity/__init__.py
gity/gity.py
gity.egg-info/PKG-INFO
gity.egg-info/SOURCES.txt
gity.egg-info/dependency_links.txt
gity.egg-info/top_level.txt