Metadata-Version: 1.0
Name: gity
Version: 0.0.1
Summary: The Git magician for Python
Home-page: https://github.com/mnw2212/gity
Author: Mayuresh Waykole
Author-email: mayuresh2212@gmail.com
License: MIT
Keywords: python git shell
Platform: any
